[{"arm7_edits":["~A MOV R0, #0","~A BX LR"],"edit_name":"OnLose game bol fal","arm8_edits":["~A8 MOV W0, WZR","~A8 RET"],"class_name":"GameManager\u0000","method_name":"OnLose"},{"arm7_edits":["~A MOV R0, #0","~A BX LR"],"edit_name":"OnLose even bol fal","arm8_edits":["~A8 MOV W0, WZR","~A8 RET"],"class_name":"EventsListener\u0000","method_name":"OnLose"},{"arm7_edits":["~A MOV R0, #0","~A BX LR"],"edit_name":"CreateTrap bol fal","arm8_edits":["~A8 MOV W0, WZR","~A8 RET"],"class_name":"GameManagerSR\u0000","method_name":"CreateTrap"},{"arm7_edits":["~A MOV R0, #0","~A BX LR"],"edit_name":"set_movesLimit bol fal","arm8_edits":["~A8 MOV W0, WZR","~A8 RET"],"class_name":"LevelData\u0000","method_name":"set_movesLimit"},{"arm7_edits":["~A MOV R0, #0","~A BX LR"],"edit_name":"sendDataDead caramelo bol fal","arm8_edits":["~A8 MOV W0, WZR","~A8 RET"],"class_name":"LevelManager\u0000","method_name":"sendDataDead"},{"arm7_edits":["~A MOV R0, #0","~A BX LR"],"edit_name":"sendDataDead burbuj bol fal","arm8_edits":["~A8 MOV W0, WZR","~A8 RET"],"class_name":"GameScreen\u0000","method_name":"sendDataDead"},{"arm7_edits":["~A MOV R0, #0","~A BX LR"],"edit_name":"ChangeHealth player bol fal","arm8_edits":["~A8 MOV W0, WZR","~A8 RET"],"class_name":"RRGPlayer\u0000","method_name":"ChangeHealth"},{"arm7_edits":["~A MOV R0, #0","~A BX LR"],"edit_name":"HitByLaser bol fal","arm8_edits":["~A8 MOV W0, WZR","~A8 RET"],"class_name":"DogController\u0000","method_name":"HitByLaser"}]